faiss_cpu-1.8.0.post1.dist-info/RECORD
faiss_cpu-1.8.0.post1.dist-info/LICENSE
faiss_cpu-1.8.0.post1.dist-info/WHEEL
faiss_cpu-1.8.0.post1.dist-info/top_level.txt
faiss_cpu-1.8.0.post1.dist-info/METADATA
faiss/_swigfaiss.cpython-310-darwin.so
faiss/class_wrappers.py
faiss/extra_wrappers.py
faiss/__init__.py
faiss/setup.py
faiss/array_conversions.py
faiss/loader.py
faiss/python_callbacks.h
faiss/_swigfaiss_avx2.cpython-310-darwin.so
faiss/gpu_wrappers.py
faiss/swigfaiss.py
faiss/swigfaiss.i
faiss/swigfaiss_avx2.py
faiss/contrib/exhaustive_search.py
faiss/contrib/ondisk.py
faiss/contrib/clustering.py
faiss/contrib/evaluation.py
faiss/contrib/datasets.py
faiss/contrib/__init__.py
faiss/contrib/factory_tools.py
faiss/contrib/rpc.py
faiss/contrib/big_batch_search.py
faiss/contrib/client_server.py
faiss/contrib/inspect_tools.py
faiss/contrib/vecs_io.py
faiss/contrib/ivf_tools.py
faiss/contrib/torch_utils.py
faiss/.dylibs/libomp.dylib
