Metadata-Version: 2.1
Name: faiss-cpu
Version: 1.8.0.post1
Summary: A library for efficient similarity search and clustering of dense vectors.
Author-email: Kota Yamaguchi <yamaguchi_kota@cyberagent.co.jp>
License: MIT License
Project-URL: Repository, https://github.com/kyamagu/faiss-wheels
Keywords: faiss,similarity search,clustering,machine learning
Classifier: Development Status :: 4 - Beta
Classifier: Intended Audience :: Developers
Classifier: Intended Audience :: Science/Research
Classifier: License :: OSI Approved :: MIT License
Classifier: Operating System :: MacOS :: MacOS X
Classifier: Operating System :: Microsoft :: Windows
Classifier: Operating System :: POSIX
Classifier: Programming Language :: Python :: 3.8
Classifier: Programming Language :: Python :: 3.9
Classifier: Programming Language :: Python :: 3.10
Classifier: Programming Language :: Python :: 3.11
Classifier: Programming Language :: Python :: 3.12
Classifier: Topic :: Scientific/Engineering :: Artificial Intelligence
Requires-Python: >=3.8
License-File: LICENSE
Requires-Dist: numpy<2.0,>=1.0
Requires-Dist: packaging
